automagik_telemetry/__init__.py
automagik_telemetry/client.py
automagik_telemetry/config.py
automagik_telemetry/opt_in.py
automagik_telemetry/privacy.py
automagik_telemetry/py.typed
automagik_telemetry/schema.py
automagik_telemetry/backends/__init__.py
automagik_telemetry/backends/clickhouse.py
automagik_telemetry-0.1.4.dist-info/METADATA
automagik_telemetry-0.1.4.dist-info/WHEEL
automagik_telemetry-0.1.4.dist-info/RECORD
