Metadata-Version: 2.4
Name: automagik-telemetry
Version: 0.1.4
Summary: Privacy-first, opt-in telemetry SDK for the Automagik ecosystem
Project-URL: Homepage, https://github.com/namastexlabs/automagik-telemetry
Project-URL: Documentation, https://github.com/namastexlabs/automagik-telemetry#readme
Project-URL: Repository, https://github.com/namastexlabs/automagik-telemetry
Project-URL: Source Code, https://github.com/namastexlabs/automagik-telemetry/tree/main/python
Project-URL: Issues, https://github.com/namastexlabs/automagik-telemetry/issues
Author-email: Automagik Team <team@namastex.ai>
License: MIT
Keywords: observability,opentelemetry,privacy,telemetry
Classifier: Development Status :: 3 - Alpha
Classifier: Intended Audience :: Developers
Classifier: License :: OSI Approved :: MIT License
Classifier: Programming Language :: Python :: 3
Classifier: Programming Language :: Python :: 3.12
Classifier: Topic :: System :: Monitoring
Requires-Python: >=3.12
Provides-Extra: dev
Requires-Dist: mypy>=1.10.0; extra == 'dev'
Requires-Dist: pytest-asyncio>=0.23.0; extra == 'dev'
Requires-Dist: pytest-cov>=4.1.0; extra == 'dev'
Requires-Dist: pytest-timeout>=2.2.0; extra == 'dev'
Requires-Dist: pytest>=8.0.0; extra == 'dev'
Requires-Dist: ruff>=0.4.0; extra == 'dev'
Provides-Extra: integration
Requires-Dist: fastapi>=0.109.0; extra == 'integration'
Requires-Dist: httpx>=0.26.0; extra == 'integration'
Requires-Dist: psutil>=5.9.0; extra == 'integration'
Requires-Dist: pytest-asyncio>=0.23.0; extra == 'integration'
Requires-Dist: pytest-timeout>=2.2.0; extra == 'integration'
Requires-Dist: pytest>=8.0.0; extra == 'integration'
